pasir/__init__.py
pasir/butiran/__init__.py
pasir/butiran/force/__init__.py
pasir/butiran/force/drag.py
pasir/butiran/force/electric.py
pasir/butiran/force/gravitational.py
pasir/butiran/force/gravitational2.py
pasir/butiran/force/magnetic.py
pasir/butiran/force/normal.py
pasir/butiran/force/normal2.py
pasir/butiran/force/spring.py
pasir/butiran/force/spring2.py
pasir/butiran/math/__init__.py
pasir/butiran/math/vect2.py
pasir/butiran/math/vect3.py
pasir/datasets/__init__.py
pasir/datasets/clasdata.py
pasir/datasets/dataviz.py
pasir/remah/__init__.py
pasir/remah/info.py
pasir-0.0.5.dist-info/LICENSE
pasir-0.0.5.dist-info/METADATA
pasir-0.0.5.dist-info/WHEEL
pasir-0.0.5.dist-info/top_level.txt
pasir-0.0.5.dist-info/RECORD
