Metadata-Version: 2.1
Name: pasir
Version: 0.0.5
Summary: granular-based simulation and related systems
Home-page: https://github.com/dudung/pasir
Author: Sparisoma Viridi
Author-email: dudung@gmail.com
License: MIT
Classifier: Programming Language :: Python :: 3
Classifier: License :: OSI Approved :: MIT License
Classifier: Operating System :: OS Independent
Requires-Python: >=3.12
License-File: LICENSE
